MANIFEST.in
README.md
setup.cfg
setup.py
django_errorlog.egg-info/PKG-INFO
django_errorlog.egg-info/SOURCES.txt
django_errorlog.egg-info/dependency_links.txt
django_errorlog.egg-info/requires.txt
django_errorlog.egg-info/top_level.txt
errorlog/__init__.py
errorlog/admin.py
errorlog/middlewares.py
errorlog/models.py
errorlog/utils.py
errorlog/migrations/0001_initial.py
errorlog/migrations/__init__.py
errorlog/vcs/__init__.py
errorlog/vcs/git.py
errorlog/vcs/hg.py