Metadata-Version: 1.1
Name: django-errorlog
Version: 0.1.1
Summary: Django reuseable app to collect the unexpcted exception then generate comprehansive report just like what you get in debug mode and store in database
Home-page: https://github.com/yjmade/django-errorlog
Author: Jay Young(yjmade)
Author-email: dev@yjmade.net
License: MIT
Keywords: django error log report
Platform: UNKNOWN
Classifier: Development Status :: 4 - Beta
Classifier: Intended Audience :: Developers
Classifier: License :: OSI Approved :: ISC License (ISCL)
Classifier: Programming Language :: Python :: 3
Classifier: Programming Language :: Python :: 3.4
Classifier: Programming Language :: Python :: 3.5
